cryptolib/__init__.py
cryptolib-0.0.2.dist-info/METADATA
cryptolib-0.0.2.dist-info/RECORD
cryptolib-0.0.2.dist-info/WHEEL
cryptolib-0.0.2.dist-info/top_level.txt
